{
	"name": "GitToRaw",
	"properties": {
		"linkedServiceName": {
			"referenceName": "HttpLinkedServer1",
			"type": "LinkedServiceReference"
		},
		"annotations": [],
		"type": "DelimitedText",
		"typeProperties": {
			"location": {
				"type": "HttpServerLocation",
				"relativeUrl": "NirmalSaudar1234/NIRMAL-ADF/blob/main/AdventureWorks_Products.csv"
			},
			"columnDelimiter": ",",
			"rowDelimiter": "\n",
			"escapeChar": "\\",
			"firstRowAsHeader": false,
			"quoteChar": null
		},
		"schema": []
	}
}